jabi.cpython-310-x86_64-linux-gnu.so
pyjabi.libs/libgcc_s-a04fdf82.so.1
pyjabi.libs/libstdc++-a9383cce.so.6.0.28
pyjabi-0.1.1.dist-info/RECORD
pyjabi-0.1.1.dist-info/METADATA
pyjabi-0.1.1.dist-info/WHEEL
pyjabi-0.1.1.dist-info/top_level.txt
