Metadata-Version: 2.1
Name: pyjabi
Version: 0.1.1
Summary: Python library for JABI (Just Another Bridge Interface)
Author-email: Matthew Tran <matthewlamtran@berkeley.edu>
Project-URL: Homepage, https://github.com/dragonlock2/JABI
Project-URL: Issues, https://github.com/dragonlock2/JABI/issues
Classifier: Programming Language :: Python :: 3
Classifier: License :: OSI Approved :: Apache Software License
Classifier: Operating System :: OS Independent
Requires-Python: >=3.9
